bytestory/__init__.py
bytestory/bytestory.py
bytestory/fields.py
bytestory-0.1.0.dist-info/WHEEL
bytestory-0.1.0.dist-info/METADATA
bytestory-0.1.0.dist-info/RECORD
