Metadata-Version: 2.1
Name: bytestory
Version: 0.1.0
Summary: Unpacking from bytes and packing into bytes, with an object interface.
Home-page: https://github.com/no1xsyzy/bytestory
License: MIT
Author: Xu Siyuan
Author-email: inqb@protonmail.com
Requires-Python: >=3.9,<4.0
Classifier: License :: OSI Approved :: MIT License
Classifier: Programming Language :: Python :: 3
Classifier: Programming Language :: Python :: 3.10
Classifier: Programming Language :: Python :: 3.9
Classifier: Topic :: Education
Project-URL: Repository, https://github.com/no1xsyzy/bytestory
